[
  {
    "title": "Oil rises after Trump threatens fresh strikes on Iran, overshadowing peace talks",
    "slug": "oil-rises-after-trump-threatens-strikes-on-iran",
    "url": "https://www.cnbc.com/2026/06/22/oil-prices-wti-brent-crude-trump-iran-threat-strait-hormuz-closure.html",
    "source": "CNBC",
    "date": "2026-06-22T00:05:08.000Z",
    "summary": "Oil prices rose Monday following President Trump's threats of military action against Iran, which could escalate regional tensions and disrupt global energy supplies. This development overshadows ongoing peace negotiations and underscores geopolitical risks affecting commodity markets.",
    "content": "Oil prices climbed on Monday after U.S. President Donald Trump threatened renewed military action against Iran.",
    "category": "economic",
    "translations": {
      "zh": {
        "title": "特朗普威胁对伊朗新一轮打击后油价上升，黯淡和平谈判前景",
        "summary": "美国总统特朗普威胁对伊朗采取军事行动后，油价于周一上升，这可能会加剧地区紧张局势并扰乱全球能源供应。这一发展黯淡了正在进行的和平谈判，并凸显了影响大宗商品市场的地缘政治风险。"
      }
    }
  }
]